cisco_eth_switch_poe/__init__.py
cisco_eth_switch_poe/cisco_eth_switch_poe.py
cisco_eth_switch_poe-0.0.1.dist-info/LICENSE
cisco_eth_switch_poe-0.0.1.dist-info/METADATA
cisco_eth_switch_poe-0.0.1.dist-info/WHEEL
cisco_eth_switch_poe-0.0.1.dist-info/top_level.txt
cisco_eth_switch_poe-0.0.1.dist-info/RECORD
