Metadata-Version: 2.1
Name: cisco-eth-switch-poe
Version: 0.0.1
Summary: python package for cisco ethernet switch POE management
Home-page: https://bitbucket.org/opsys_tech/cisco-eth-switch-poe/src/master/
Download-URL: https://bitbucket.org/opsys_tech/cisco-eth-switch-poe/src/master/
Author: dmitry.borovensky
Author-email: dmitry.borovensky@opsys-tech.com
License-File: LICENSE
